dtokenizer/__init__.py
dtokenizer/interface.py
dtokenizer/audio/__init__.py
dtokenizer/audio/utility.py
dtokenizer/audio/model/__init__.py
dtokenizer/audio/model/encodec_model/__init__.py
dtokenizer/audio/model/encodec_model/configuration_encodec.py
dtokenizer/audio/model/hubert/__init__.py
dtokenizer/audio/model/hubert/configuration_hubert.py
dtokenizer/audio/model/hubert/modeling_hubert.py
dtokenizer/audio/model/hubert_model/__init__.py
dtokenizer/audio/model/hubert_model/configuration_hubert.py
dtokenizer/audio/model/hubert_model/modeling_hubert.py
dtokenizer/audio/model/semanticodec_model/__init__.py
dtokenizer/audio/model/semanticodec_model/configuration_semanticodec.py
dtokenizer/audio/vocoder/__init__.py
dtokenizer/audio/vocoder/hifigan.py
dtokenizer/image/__init__.py
dtokenizer-0.0.6.dist-info/LICENSE
dtokenizer-0.0.6.dist-info/METADATA
dtokenizer-0.0.6.dist-info/WHEEL
dtokenizer-0.0.6.dist-info/top_level.txt
dtokenizer-0.0.6.dist-info/RECORD
