Metadata-Version: 2.1
Name: dtokenizer
Version: 0.0.6
Home-page: https://github.com/voidful/dtokenizer
Author: Voidful
Author-email: voidful.stack@gmail.com
License: Apache
Keywords: tokenizer
Classifier: Development Status :: 4 - Beta
Classifier: License :: OSI Approved :: Apache Software License
Classifier: Programming Language :: Python
License-File: LICENSE
